README.md
setup.py
remanu/__init__.py
remanu/lab.py
remanu/sequence.py
remanu.egg-info/PKG-INFO
remanu.egg-info/SOURCES.txt
remanu.egg-info/dependency_links.txt
remanu.egg-info/top_level.txt